README.md
setup.py
btcsignature/__init__.py
btcsignature/command_line.py
btcsignature/offlinesig.py
btcsignature.egg-info/PKG-INFO
btcsignature.egg-info/SOURCES.txt
btcsignature.egg-info/dependency_links.txt
btcsignature.egg-info/entry_points.txt
btcsignature.egg-info/not-zip-safe
btcsignature.egg-info/requires.txt
btcsignature.egg-info/top_level.txt