Metadata-Version: 1.0
Name: btcsignature
Version: 0.13
Summary: secure offline bitcoin transaction signing tool
Home-page: http://github.com/superarius/sendbtcsimply/
Author: sendbtcsimply
Author-email: sendbtcsimply@protonmail.com
License: MIT
Platform: UNKNOWN
